genyal/__init__.py
genyal/core.py
genyal/engine.py
genyal/genotype.py
genyal/individuals.py
genyal/population.py
genyal/operations/__init__.py
genyal/operations/crossover.py
genyal/operations/evolution.py
genyal/operations/mutation.py
test/__init__.py
test/test_population.py
genyal-0.2.1.dist-info/METADATA
genyal-0.2.1.dist-info/WHEEL
genyal-0.2.1.dist-info/top_level.txt
genyal-0.2.1.dist-info/RECORD
