Metadata-Version: 2.1
Name: genyal
Version: 0.2.1
Summary: A framework for genetic algorithms in Python
Home-page: https://github.com/islaterm/genyal
Author: Ignacio Slater Muñoz
Author-email: islaterm@gmail.com
License: UNKNOWN
Platform: UNKNOWN
Classifier: Programming Language :: Python :: 3
Classifier: Operating System :: OS Independent
Requires-Python: >=3.9
